setup.py
liquipy/__init__.py
liquipy/changeset.py
liquipy/db.py
liquipy/executor.py
liquipy/version.py
liquipy.egg-info/PKG-INFO
liquipy.egg-info/SOURCES.txt
liquipy.egg-info/dependency_links.txt
liquipy.egg-info/not-zip-safe
liquipy.egg-info/requires.txt
liquipy.egg-info/top_level.txt
liquipy/externals/liquibase.jar
liquipy/externals/mysql-connector-java-5.1.17-bin.jar