Metadata-Version: 1.1
Name: liquipy
Version: 0.1.4
Summary: a Python wrapper for Liquibase (see http://www.liquibase.org/)
Home-page: http://github.com/groksolutions/liquipy
Author: Matthew Taylor
Author-email: matt@groksolutions.com
License: Apache
Download-URL: https://pypi.python.org/packages/source/g/liquipy/liquipy-0.1.4.tar.gz
Keywords: sql,migrations,liquibase
Platform: UNKNOWN
Classifier: Development Status :: 1 - Planning
Classifier: Environment :: Console
Classifier: Intended Audience :: Developers
Classifier: License :: OSI Approved :: Apache Software License
Classifier: Natural Language :: English
Classifier: Operating System :: OS Independent
Classifier: Programming Language :: Python
